{
  "title": "Marham.pk Doctors Scraper",
  "description": "Extract doctor listings from Marham.pk, Pakistan's leading healthcare platform. Search by specialty and city to find verified doctors with qualifications, fees, reviews, and contact information using sitemap and JSON-LD extraction.",
  "type": "object",
  "schemaVersion": 1,
  "properties": {
    "startUrls": {
      "title": "Start URLs (optional)",
      "type": "array",
      "description": "Array of Marham.pk doctor profile URLs to scrape. If provided, specialty and city filters will be ignored.",
      "editor": "stringList"
    },
    "specialty": {
      "title": "Doctor Specialty",
      "type": "string",
      "description": "Medical specialty to search for (e.g., 'dermatologist', 'cardiologist', 'pediatrician', 'gynecologist', 'orthopedic', 'neurologist').",
      "editor": "textfield",
      "prefill": "dermatologist",
      "default": "dermatologist"
    },
    "city": {
      "title": "City",
      "type": "string",
      "description": "City to search in (e.g., 'lahore', 'karachi', 'islamabad', 'rawalpindi', 'faisalabad'). Leave empty for all cities.",
      "editor": "textfield",
      "prefill": "lahore",
      "default": "lahore"
    },
    "results_wanted": {
      "title": "Maximum number of doctors",
      "type": "integer",
      "description": "Maximum number of doctor profiles to collect from the sitemap.",
      "minimum": 1,
      "maximum": 1000,
      "default": 50,
      "editor": "number"
    },
    "proxyConfiguration": {
      "title": "Proxy configuration",
      "type": "object",
      "description": "Proxy settings for scraping. Residential proxies recommended for better reliability.",
      "editor": "proxy",
      "default": {
        "useApifyProxy": true,
        "apifyProxyGroups": [
          "RESIDENTIAL"
        ]
      }
    }
  },
  "required": [],
  "additionalProperties": false
}